{
    "company": {
        "id": "DABUR",
        "company_logo": "https://bluestock.in/static/mkt-icons/nifty100/DABUR.png",
        "company_name": "Dabur India Ltd",
        "chart_link": "https://in.tradingview.com/chart/?symbol=NSE%3ADABUR",
        "about_company": "Dabur India is one of the leading fast moving consumer goods (FMCG) players dealing in consumer care and food products.",
        "website": "http://www.dabur.com/",
        "nse_profile": "https://www.nseindia.com/get-quotes/equity?symbol=DABUR",
        "bse_profile": "https://www.bseindia.com/stock-share-price/dabur-india-ltd/DABUR/500096/",
        "face_value": 1,
        "book_value": 59,
        "roce_percentage": "22.30",
        "roe_percentage": "19.20"
    },
    "data": {
        "cashflow": [
            {
                "id": 398,
                "company_id": "DABUR",
                "year": "Mar 2013",
                "operating_activity": 870,
                "investing_activity": -622,
                "financing_activity": -234,
                "net_cash_flow": 13
            },
            {
                "id": 399,
                "company_id": "DABUR",
                "year": "Mar 2014",
                "operating_activity": 1098,
                "investing_activity": -104,
                "financing_activity": -804,
                "net_cash_flow": 190
            },
            {
                "id": 400,
                "company_id": "DABUR",
                "year": "Mar 2015",
                "operating_activity": 1047,
                "investing_activity": -876,
                "financing_activity": -417,
                "net_cash_flow": -245
            },
            {
                "id": 401,
                "company_id": "DABUR",
                "year": "Mar 2016",
                "operating_activity": 1187,
                "investing_activity": -730,
                "financing_activity": -374,
                "net_cash_flow": 82
            },
            {
                "id": 402,
                "company_id": "DABUR",
                "year": "Mar 2017",
                "operating_activity": 1227,
                "investing_activity": -807,
                "financing_activity": -339,
                "net_cash_flow": 81
            },
            {
                "id": 403,
                "company_id": "DABUR",
                "year": "Mar 2018",
                "operating_activity": 1092,
                "investing_activity": -541,
                "financing_activity": -577,
                "net_cash_flow": -27
            },
            {
                "id": 404,
                "company_id": "DABUR",
                "year": "Mar 2019",
                "operating_activity": 1499,
                "investing_activity": 338,
                "financing_activity": -1888,
                "net_cash_flow": -51
            },
            {
                "id": 405,
                "company_id": "DABUR",
                "year": "Mar 2020",
                "operating_activity": 1614,
                "investing_activity": -517,
                "financing_activity": -1043,
                "net_cash_flow": 54
            },
            {
                "id": 406,
                "company_id": "DABUR",
                "year": "Mar 2021",
                "operating_activity": 2115,
                "investing_activity": -1404,
                "financing_activity": -613,
                "net_cash_flow": 97
            },
            {
                "id": 407,
                "company_id": "DABUR",
                "year": "Mar 2022",
                "operating_activity": 1802,
                "investing_activity": -1273,
                "financing_activity": -490,
                "net_cash_flow": 38
            },
            {
                "id": 408,
                "company_id": "DABUR",
                "year": "Mar 2023",
                "operating_activity": 1488,
                "investing_activity": -583,
                "financing_activity": -1035,
                "net_cash_flow": -130
            },
            {
                "id": 409,
                "company_id": "DABUR",
                "year": "Mar 2024",
                "operating_activity": 2013,
                "investing_activity": -971,
                "financing_activity": -1161,
                "net_cash_flow": -119
            }
        ],
        "prosandcons": [],
        "balancesheet": [
            {
                "id": 490,
                "company_id": "DABUR",
                "year": "Mar 2013",
                "equity_capital": "174.0",
                "reserves": 1921,
                "borrowings": 1151,
                "other_liabilities": 1462,
                "total_liabilities": 4709,
                "fixed_assets": 1582,
                "cwip": 93,
                "investments": 929,
                "other_asset": 2105,
                "total_assets": 4709
            },
            {
                "id": 491,
                "company_id": "DABUR",
                "year": "Mar 2014",
                "equity_capital": "174.0",
                "reserves": 2482,
                "borrowings": 708,
                "other_liabilities": 1948,
                "total_liabilities": 5312,
                "fixed_assets": 1767,
                "cwip": 22,
                "investments": 1076,
                "other_asset": 2447,
                "total_assets": 5312
            },
            {
                "id": 492,
                "company_id": "DABUR",
                "year": "Mar 2015",
                "equity_capital": "176.0",
                "reserves": 3178,
                "borrowings": 734,
                "other_liabilities": 2019,
                "total_liabilities": 6106,
                "fixed_assets": 1877,
                "cwip": 50,
                "investments": 1813,
                "other_asset": 2365,
                "total_assets": 6106
            },
            {
                "id": 493,
                "company_id": "DABUR",
                "year": "Mar 2016",
                "equity_capital": "176.0",
                "reserves": 3995,
                "borrowings": 805,
                "other_liabilities": 1956,
                "total_liabilities": 6932,
                "fixed_assets": 1667,
                "cwip": 45,
                "investments": 2691,
                "other_asset": 2529,
                "total_assets": 6932
            },
            {
                "id": 494,
                "company_id": "DABUR",
                "year": "Mar 2017",
                "equity_capital": "176.0",
                "reserves": 4671,
                "borrowings": 975,
                "other_liabilities": 1910,
                "total_liabilities": 7732,
                "fixed_assets": 1958,
                "cwip": 42,
                "investments": 3240,
                "other_asset": 2492,
                "total_assets": 7732
            },
            {
                "id": 495,
                "company_id": "DABUR",
                "year": "Mar 2018",
                "equity_capital": "176.0",
                "reserves": 5530,
                "borrowings": 938,
                "other_liabilities": 2058,
                "total_liabilities": 8702,
                "fixed_assets": 2028,
                "cwip": 42,
                "investments": 3805,
                "other_asset": 2827,
                "total_assets": 8702
            },
            {
                "id": 496,
                "company_id": "DABUR",
                "year": "Mar 2019",
                "equity_capital": "177.0",
                "reserves": 5455,
                "borrowings": 699,
                "other_liabilities": 2106,
                "total_liabilities": 8437,
                "fixed_assets": 1969,
                "cwip": 64,
                "investments": 3359,
                "other_asset": 3045,
                "total_assets": 8437
            },
            {
                "id": 497,
                "company_id": "DABUR",
                "year": "Mar 2020",
                "equity_capital": "177.0",
                "reserves": 6429,
                "borrowings": 522,
                "other_liabilities": 2209,
                "total_liabilities": 9337,
                "fixed_assets": 2253,
                "cwip": 147,
                "investments": 2800,
                "other_asset": 4137,
                "total_assets": 9337
            },
            {
                "id": 498,
                "company_id": "DABUR",
                "year": "Mar 2021",
                "equity_capital": "177.0",
                "reserves": 7487,
                "borrowings": 509,
                "other_liabilities": 2661,
                "total_liabilities": 10833,
                "fixed_assets": 2243,
                "cwip": 147,
                "investments": 4160,
                "other_asset": 4283,
                "total_assets": 10833
            },
            {
                "id": 499,
                "company_id": "DABUR",
                "year": "Mar 2022",
                "equity_capital": "177.0",
                "reserves": 8205,
                "borrowings": 1030,
                "other_liabilities": 2872,
                "total_liabilities": 12284,
                "fixed_assets": 2308,
                "cwip": 168,
                "investments": 6220,
                "other_asset": 3589,
                "total_assets": 12284
            },
            {
                "id": 500,
                "company_id": "DABUR",
                "year": "Mar 2023",
                "equity_capital": "177.0",
                "reserves": 8796,
                "borrowings": 1174,
                "other_liabilities": 3505,
                "total_liabilities": 13652,
                "fixed_assets": 3579,
                "cwip": 175,
                "investments": 6265,
                "other_asset": 3633,
                "total_assets": 13652
            },
            {
                "id": 501,
                "company_id": "DABUR",
                "year": "Mar 2024",
                "equity_capital": "177.0",
                "reserves": 9689,
                "borrowings": 1365,
                "other_liabilities": 3885,
                "total_liabilities": 15116,
                "fixed_assets": 3815,
                "cwip": 232,
                "investments": 6933,
                "other_asset": 4136,
                "total_assets": 15116
            },
            {
                "id": 502,
                "company_id": "DABUR",
                "year": "Sep 2024",
                "equity_capital": "177.0",
                "reserves": 10185,
                "borrowings": 1752,
                "other_liabilities": 4259,
                "total_liabilities": 16373,
                "fixed_assets": 3874,
                "cwip": 190,
                "investments": 7599,
                "other_asset": 4710,
                "total_assets": 16373
            }
        ],
        "profitandloss": [
            {
                "id": 412,
                "company_id": "DABUR",
                "year": "Mar 2013",
                "sales": 6140,
                "expenses": 5148,
                "operating_profit": 992,
                "opm_percentage": 16,
                "other_income": 100,
                "interest": 59,
                "depreciation": 85,
                "profit_before_tax": 948,
                "tax_percentage": "19",
                "net_profit": 766,
                "eps": 4,
                "dividend_payout": "34"
            },
            {
                "id": 413,
                "company_id": "DABUR",
                "year": "Mar 2014",
                "sales": 7058,
                "expenses": 5897,
                "operating_profit": 1162,
                "opm_percentage": 16,
                "other_income": 126,
                "interest": 54,
                "depreciation": 97,
                "profit_before_tax": 1136,
                "tax_percentage": "19",
                "net_profit": 916,
                "eps": 5,
                "dividend_payout": "33"
            },
            {
                "id": 414,
                "company_id": "DABUR",
                "year": "Mar 2015",
                "sales": 7795,
                "expenses": 6475,
                "operating_profit": 1320,
                "opm_percentage": 17,
                "other_income": 154,
                "interest": 40,
                "depreciation": 115,
                "profit_before_tax": 1319,
                "tax_percentage": "19",
                "net_profit": 1068,
                "eps": 6,
                "dividend_payout": "33"
            },
            {
                "id": 415,
                "company_id": "DABUR",
                "year": "Mar 2016",
                "sales": 7780,
                "expenses": 6261,
                "operating_profit": 1518,
                "opm_percentage": 20,
                "other_income": 217,
                "interest": 48,
                "depreciation": 133,
                "profit_before_tax": 1554,
                "tax_percentage": "19",
                "net_profit": 1254,
                "eps": 7,
                "dividend_payout": "32"
            },
            {
                "id": 416,
                "company_id": "DABUR",
                "year": "Mar 2017",
                "sales": 7614,
                "expenses": 6102,
                "operating_profit": 1512,
                "opm_percentage": 20,
                "other_income": 296,
                "interest": 54,
                "depreciation": 143,
                "profit_before_tax": 1611,
                "tax_percentage": "21",
                "net_profit": 1280,
                "eps": 7,
                "dividend_payout": "31"
            },
            {
                "id": 417,
                "company_id": "DABUR",
                "year": "Mar 2018",
                "sales": 7722,
                "expenses": 6104,
                "operating_profit": 1617,
                "opm_percentage": 21,
                "other_income": 291,
                "interest": 53,
                "depreciation": 162,
                "profit_before_tax": 1693,
                "tax_percentage": "20",
                "net_profit": 1358,
                "eps": 8,
                "dividend_payout": "81"
            },
            {
                "id": 418,
                "company_id": "DABUR",
                "year": "Mar 2019",
                "sales": 8515,
                "expenses": 6775,
                "operating_profit": 1740,
                "opm_percentage": 20,
                "other_income": 222,
                "interest": 60,
                "depreciation": 177,
                "profit_before_tax": 1725,
                "tax_percentage": "16",
                "net_profit": 1446,
                "eps": 8,
                "dividend_payout": "34"
            },
            {
                "id": 419,
                "company_id": "DABUR",
                "year": "Mar 2020",
                "sales": 8685,
                "expenses": 6892,
                "operating_profit": 1792,
                "opm_percentage": 21,
                "other_income": 205,
                "interest": 50,
                "depreciation": 220,
                "profit_before_tax": 1728,
                "tax_percentage": "16",
                "net_profit": 1448,
                "eps": 8,
                "dividend_payout": "37"
            },
            {
                "id": 420,
                "company_id": "DABUR",
                "year": "Mar 2021",
                "sales": 9562,
                "expenses": 7560,
                "operating_profit": 2002,
                "opm_percentage": 21,
                "other_income": 325,
                "interest": 31,
                "depreciation": 240,
                "profit_before_tax": 2056,
                "tax_percentage": "18",
                "net_profit": 1695,
                "eps": 10,
                "dividend_payout": "50"
            },
            {
                "id": 421,
                "company_id": "DABUR",
                "year": "Mar 2022",
                "sales": 10889,
                "expenses": 8637,
                "operating_profit": 2252,
                "opm_percentage": 21,
                "other_income": 308,
                "interest": 39,
                "depreciation": 253,
                "profit_before_tax": 2269,
                "tax_percentage": "23",
                "net_profit": 1742,
                "eps": 10,
                "dividend_payout": "53"
            },
            {
                "id": 422,
                "company_id": "DABUR",
                "year": "Mar 2023",
                "sales": 11530,
                "expenses": 9367,
                "operating_profit": 2162,
                "opm_percentage": 19,
                "other_income": 445,
                "interest": 78,
                "depreciation": 311,
                "profit_before_tax": 2219,
                "tax_percentage": "23",
                "net_profit": 1701,
                "eps": 10,
                "dividend_payout": "54"
            },
            {
                "id": 423,
                "company_id": "DABUR",
                "year": "Mar 2024",
                "sales": 12404,
                "expenses": 10004,
                "operating_profit": 2400,
                "opm_percentage": 19,
                "other_income": 482,
                "interest": 124,
                "depreciation": 399,
                "profit_before_tax": 2359,
                "tax_percentage": "23",
                "net_profit": 1811,
                "eps": 10,
                "dividend_payout": "53"
            },
            {
                "id": 424,
                "company_id": "DABUR",
                "year": "TTM",
                "sales": 12447,
                "expenses": 10106,
                "operating_profit": 2341,
                "opm_percentage": 19,
                "other_income": 537,
                "interest": 152,
                "depreciation": 424,
                "profit_before_tax": 2302,
                "tax_percentage": null,
                "net_profit": 1760,
                "eps": 10,
                "dividend_payout": null
            }
        ],
        "analysis": [],
        "documents": [
            {
                "id": 417,
                "company_id": "DABUR",
                "Year": 2024,
                "Annual_Report": "https://www.bseindia.com/xml-data/corpfiling/AttachHis/b6f3ff71-f4ec-428e-a42f-7cb240b20049.pdf"
            },
            {
                "id": 418,
                "company_id": "DABUR",
                "Year": 2023,
                "Annual_Report": "https://www.bseindia.com/xml-data/corpfiling/AttachHis//a8dfb6ee-147c-45ab-8d51-4a7fc4ebfacb.pdf"
            },
            {
                "id": 419,
                "company_id": "DABUR",
                "Year": 2022,
                "Annual_Report": "https://www.bseindia.com/bseplus/AnnualReport/500096/73713500096.pdf"
            },
            {
                "id": 420,
                "company_id": "DABUR",
                "Year": 2021,
                "Annual_Report": "https://www.bseindia.com/bseplus/AnnualReport/500096/69003500096_28_07_21.pdf"
            },
            {
                "id": 421,
                "company_id": "DABUR",
                "Year": 2020,
                "Annual_Report": "https://www.bseindia.com/bseplus/AnnualReport/500096/5000960320.pdf"
            },
            {
                "id": 422,
                "company_id": "DABUR",
                "Year": 2019,
                "Annual_Report": "https://www.bseindia.com/bseplus/AnnualReport/500096/5000960319.pdf"
            },
            {
                "id": 423,
                "company_id": "DABUR",
                "Year": 2018,
                "Annual_Report": "https://www.bseindia.com/bseplus/AnnualReport/500096/5000960318.pdf"
            },
            {
                "id": 424,
                "company_id": "DABUR",
                "Year": 2017,
                "Annual_Report": "https://www.bseindia.com/bseplus/AnnualReport/500096/5000960317.pdf"
            },
            {
                "id": 425,
                "company_id": "DABUR",
                "Year": 2016,
                "Annual_Report": "https://www.bseindia.com/bseplus/AnnualReport/500096/5000960316.pdf"
            },
            {
                "id": 426,
                "company_id": "DABUR",
                "Year": 2015,
                "Annual_Report": "https://www.bseindia.com/bseplus/AnnualReport/500096/5000960315.pdf"
            },
            {
                "id": 427,
                "company_id": "DABUR",
                "Year": 2014,
                "Annual_Report": "https://www.bseindia.com/bseplus/AnnualReport/500096/5000960314.pdf"
            },
            {
                "id": 428,
                "company_id": "DABUR",
                "Year": 2013,
                "Annual_Report": "https://www.bseindia.com/bseplus/AnnualReport/500096/5000960313.pdf"
            },
            {
                "id": 429,
                "company_id": "DABUR",
                "Year": 2012,
                "Annual_Report": "https://www.bseindia.com/bseplus/AnnualReport/500096/5000960312.pdf"
            },
            {
                "id": 430,
                "company_id": "DABUR",
                "Year": 2011,
                "Annual_Report": "https://www.bseindia.com/bseplus/AnnualReport/500096/5000960311.pdf"
            },
            {
                "id": 431,
                "company_id": "DABUR",
                "Year": 2010,
                "Annual_Report": "Null"
            },
            {
                "id": 432,
                "company_id": "DABUR",
                "Year": 2009,
                "Annual_Report": "Null"
            }
        ]
    }
}